fsmhub/__init__.py
fsmhub/app.py
fsmhub/core.py
fsmhub/entities.py
fsmhub-4.8.1.data/scripts/fsm-step
fsmhub-4.8.1.dist-info/METADATA
fsmhub-4.8.1.dist-info/WHEEL
fsmhub-4.8.1.dist-info/top_level.txt
fsmhub-4.8.1.dist-info/RECORD
