Metadata-Version: 2.1
Name: fsmhub
Version: 4.8.1
Summary: Finite State Machine storage hub
Home-page: https://github.com/lwzm/fsmhub
Author: lwzm
Author-email: lwzm@qq.com
License: UNKNOWN
Keywords: fsm,http,web,store
Platform: UNKNOWN
Classifier: Environment :: Console
Classifier: Programming Language :: Python :: 3
Requires-Dist: pony
Requires-Dist: fastapi
Requires-Dist: uvicorn
